anya_table/AnyaTable.py
anya_table/AnyaTheme.py
anya_table/AnyaTitle.py
anya_table/Table.py
anya_table/__init__.py
anya_table/_imports_.py
anya_table/anya_table.min.js
anya_table/anya_table.min.js.map
anya_table/async-AntTable.js
anya_table/async-AntTable.js.map
anya_table/async-AnyaTable.js
anya_table/async-AnyaTable.js.map
anya_table/comm.py
anya_table/metadata.json
anya_table/package-info.json
anya_table-0.0.6.dist-info/LICENSE
anya_table-0.0.6.dist-info/METADATA
anya_table-0.0.6.dist-info/WHEEL
anya_table-0.0.6.dist-info/top_level.txt
anya_table-0.0.6.dist-info/RECORD
